{
  "type": "minecraft:blasting",
  "category": "misc",
  "cookingtime": 100,
  "experience": 0.1,
  "group": "aluminium",
  "ingredient": [
    {
      "item": "more-ores:bronze_pickaxe"
    },
    {
      "item": "more-ores:bronze_shovel"
    },
    {
      "item": "more-ores:bronze_axe"
    },
    {
      "item": "more-ores:bronze_hoe"
    },
    {
      "item": "more-ores:bronze_sword"
    },
    {
      "item": "more-ores:bronze_helmet"
    },
    {
      "item": "more-ores:bronze_chestplate"
    },
    {
      "item": "more-ores:bronze_leggings"
    },
    {
      "item": "more-ores:bronze_boots"
    },
    {
      "item": "more-ores:bronze_alloy"
    }
  ],
  "result": {
    "id": "more-ores:bronze_ingot"
  }
}